graphgp/__init__.py
graphgp/extras.py
graphgp/graph.py
graphgp/refine.py
graphgp/tree.py
graphgp-0.0.2.dist-info/METADATA
graphgp-0.0.2.dist-info/WHEEL
graphgp-0.0.2.dist-info/licenses/LICENSE
graphgp-0.0.2.dist-info/RECORD
