Metadata-Version: 2.4
Name: graphgp
Version: 0.0.2
Summary: Scalable Gaussian processes with nearest neighbor graphs.
Project-URL: Source, https://github.com/stanford-ism/graphgp
Author-email: Benjamin Dodge <bendodge@stanford.edu>, Philipp Frank <phfrank@stanford.edu>
License-File: LICENSE
Requires-Python: >=3.10
Requires-Dist: jax
Provides-Extra: cuda
Requires-Dist: graphgp-cuda; extra == 'cuda'
Provides-Extra: dev
Requires-Dist: ipywidgets>=8.1.7; extra == 'dev'
Requires-Dist: jax[cuda12]==0.8.0; extra == 'dev'
Requires-Dist: jaxkd[cuda]; extra == 'dev'
Requires-Dist: jupyterlab>=4.4.3; extra == 'dev'
Requires-Dist: matplotlib>=3.10.3; extra == 'dev'
Requires-Dist: optax; extra == 'dev'
Requires-Dist: pytest>=8.3.5; extra == 'dev'
Requires-Dist: ruff>=0.11.11; extra == 'dev'
Requires-Dist: scipy; extra == 'dev'
Requires-Dist: tqdm>=4.67.1; extra == 'dev'
